OBP_devops/__init__.py
OBP_devops/cloudformation.py
OBP_devops/codebuild.py
OBP_devops/codedeploy_auto_rollback_monitor_enabled.py
OBP_devops/codedeploy_ec2_minimum_healthy_hosts_configured.py
OBP_devops/codedeploy_lambda_allatonce_traffic_shift_disabled.py
OBP_devops/codepipeline.py
OBP_devops/ecr.py
OBP_devops/ecr_private_tag_immutability_enabled.py
OBP_devops/ecs_container_insights_enabled.py
OBP_devops/ecs_containers_non_privileged.py
OBP_devops/ecs_containers_read_only_access.py
OBP_devops/ecs_fargate_latest_platform_version.py
OBP_devops/ecs_task_definition_memory_hard_limit.py
OBP_devops/ecs_task_definition_nonroot_user.py
OBP_devops/ecs_task_definition_pid_mode_check.py
OBP_devops/ecs_task_definition_user_for_host_mode_check.py
OBP_devops/eks.py
OBP_devops/elastic_beanstalk.py
OBP_devops/utils.py
OBP_devops-0.2.1.dist-info/METADATA
OBP_devops-0.2.1.dist-info/WHEEL
OBP_devops-0.2.1.dist-info/top_level.txt
OBP_devops-0.2.1.dist-info/RECORD
